Rocketstore/Rocketstore.py
Rocketstore/__init__.py
Rocketstore/__version__.py
Rocketstore/utils/__init__.py
Rocketstore/utils/files.py
Rocket_Store-0.0.10.dist-info/LICENSE
Rocket_Store-0.0.10.dist-info/METADATA
Rocket_Store-0.0.10.dist-info/WHEEL
Rocket_Store-0.0.10.dist-info/top_level.txt
Rocket_Store-0.0.10.dist-info/RECORD
