Metadata-Version: 2.1
Name: Rocket-Store
Version: 0.0.10
Summary: Using the filesystem as a searchable database.
Author-email: Anton Sychev <anton@sychev.xyz>
License: Rocket Store
Project-URL: Homepage, https://github.com/klich3/rocket-store-python
Project-URL: Issues, https://github.com/klich3/rocket-store-python/issues
Keywords: database,store,file,document,database-mangement,record,file-store,store-file,filebase
Classifier: Programming Language :: Python :: 3
Classifier: License :: OSI Approved :: MIT License
Classifier: Operating System :: OS Independent
Requires-Python: >=3.8
License-File: LICENSE
Provides-Extra: build
Requires-Dist: build ; extra == 'build'
Requires-Dist: twine ; extra == 'build'
